{"version":{"fullVersion":"1.6.1","major":"1","minor":"6","patch":"1"},"meta":{"flags":["experimentalData"]},"collections":[{"name":"header","label":"Header","path":"content/components/Header","format":"md","match":{"include":"header"},"fields":[{"type":"image","name":"logo","label":"Logo Image","namespace":["header","logo"],"searchable":false,"uid":false},{"type":"object","name":"menuItems","label":"Menu Items","list":true,"fields":[{"type":"string","name":"label","label":"Menu Label","namespace":["header","menuItems","label"],"searchable":true,"uid":false},{"type":"string","name":"url","label":"URL","required":false,"namespace":["header","menuItems","url"],"searchable":true,"uid":false},{"type":"object","name":"subItems","label":"Dropdown Items","list":true,"fields":[{"type":"string","name":"label","label":"Submenu Label","namespace":["header","menuItems","subItems","label"],"searchable":true,"uid":false},{"type":"string","name":"url","label":"Submenu URL","namespace":["header","menuItems","subItems","url"],"searchable":true,"uid":false}],"namespace":["header","menuItems","subItems"],"searchable":true,"uid":false}],"namespace":["header","menuItems"],"searchable":true,"uid":false},{"type":"string","name":"loginText","label":"Login Button Text","namespace":["header","loginText"],"searchable":true,"uid":false},{"type":"string","name":"registerText","label":"Register Button Text","namespace":["header","registerText"],"searchable":true,"uid":false},{"type":"object","name":"contactInfo","label":"Contact Info","list":true,"fields":[{"type":"string","name":"label","label":"Label","namespace":["header","contactInfo","label"],"searchable":true,"uid":false},{"type":"string","name":"url","label":"URL","namespace":["header","contactInfo","url"],"searchable":true,"uid":false},{"type":"image","name":"desktopIcon","label":"Desktop Icon","namespace":["header","contactInfo","desktopIcon"],"searchable":false,"uid":false},{"type":"image","name":"mobileIcon","label":"Mobile Icon","namespace":["header","contactInfo","mobileIcon"],"searchable":false,"uid":false},{"type":"image","name":"flag","label":"Flag (optional)","namespace":["header","contactInfo","flag"],"searchable":false,"uid":false}],"namespace":["header","contactInfo"],"searchable":true,"uid":false}],"namespace":["header"]},{"name":"hero","label":"Hero Section","path":"content/pages/Home","format":"md","match":{"include":"hero"},"fields":[{"type":"string","name":"title","label":"Title","namespace":["hero","title"],"searchable":true,"uid":false},{"type":"string","name":"subtitle","label":"Subtitle","namespace":["hero","subtitle"],"searchable":true,"uid":false},{"type":"image","name":"backgroundImage","label":"Background Image","namespace":["hero","backgroundImage"],"searchable":false,"uid":false},{"type":"image","name":"backgroundImageForMobile","label":"Background Image For Mobile","namespace":["hero","backgroundImageForMobile"],"searchable":false,"uid":false},{"type":"string","name":"primaryCta","label":"Primary Button Text","namespace":["hero","primaryCta"],"searchable":true,"uid":false},{"type":"string","name":"primaryCtaUrl","label":"Primary Button URL","namespace":["hero","primaryCtaUrl"],"searchable":true,"uid":false},{"type":"string","name":"secondaryCta","label":"Secondary Button Text","namespace":["hero","secondaryCta"],"searchable":true,"uid":false},{"type":"string","name":"secondaryCtaUrl","label":"Secondary Button URL","namespace":["hero","secondaryCtaUrl"],"searchable":true,"uid":false}],"namespace":["hero"]},{"name":"organizations","label":"Organizations","path":"content/pages/Home","format":"md","match":{"include":"organizations"},"fields":[{"type":"string","name":"title","label":"Section Title","namespace":["organizations","title"],"searchable":true,"uid":false},{"type":"object","name":"logos","label":"Organization Logos","list":true,"fields":[{"type":"image","name":"src","label":"Logo Image","namespace":["organizations","logos","src"],"searchable":false,"uid":false}],"namespace":["organizations","logos"],"searchable":true,"uid":false}],"namespace":["organizations"]},{"name":"ourSolutions","label":"Our Solutions","path":"content/pages/Home","format":"md","match":{"include":"our-solutions"},"fields":[{"type":"string","name":"title","label":"Section Title","namespace":["ourSolutions","title"],"searchable":true,"uid":false},{"type":"object","name":"leftSolutions","label":"Left Grid Solutions","list":true,"fields":[{"type":"string","name":"title","label":"Solution Title","namespace":["ourSolutions","leftSolutions","title"],"searchable":true,"uid":false},{"type":"image","name":"backgroundImage","label":"Background Image","namespace":["ourSolutions","leftSolutions","backgroundImage"],"searchable":false,"uid":false},{"type":"boolean","name":"highlight","label":"Yellow Highlight Box?","namespace":["ourSolutions","leftSolutions","highlight"],"searchable":true,"uid":false}],"namespace":["ourSolutions","leftSolutions"],"searchable":true,"uid":false},{"type":"image","name":"rightImage","label":"Big Right Image","namespace":["ourSolutions","rightImage"],"searchable":false,"uid":false},{"type":"object","name":"solutionsList","label":"Small Solutions List","list":true,"fields":[{"type":"string","name":"label","label":"Solution Label","namespace":["ourSolutions","solutionsList","label"],"searchable":true,"uid":false}],"namespace":["ourSolutions","solutionsList"],"searchable":true,"uid":false},{"type":"string","name":"ctaText","label":"CTA Button Text","namespace":["ourSolutions","ctaText"],"searchable":true,"uid":false}],"namespace":["ourSolutions"]},{"name":"trustedBy","label":"Trusted By","path":"content/pages/Home","format":"md","match":{"include":"trusted-by"},"fields":[{"type":"string","name":"title","label":"Main Title","namespace":["trustedBy","title"],"searchable":true,"uid":false},{"type":"object","name":"stats","label":"Stats","list":true,"fields":[{"type":"string","name":"title","label":"Stat Title","namespace":["trustedBy","stats","title"],"searchable":true,"uid":false},{"type":"string","name":"subtitle","label":"Stat Subtitle","namespace":["trustedBy","stats","subtitle"],"searchable":true,"uid":false}],"namespace":["trustedBy","stats"],"searchable":true,"uid":false},{"type":"object","name":"reviews","label":"Customer Reviews","list":true,"fields":[{"type":"string","name":"review","label":"Review Text","namespace":["trustedBy","reviews","review"],"searchable":true,"uid":false},{"type":"string","name":"name","label":"Reviewer Name","namespace":["trustedBy","reviews","name"],"searchable":true,"uid":false},{"type":"string","name":"position","label":"Reviewer Position","namespace":["trustedBy","reviews","position"],"searchable":true,"uid":false}],"namespace":["trustedBy","reviews"],"searchable":true,"uid":false}],"namespace":["trustedBy"]},{"name":"highQualitySolutions","label":"High Quality Solutions","path":"content/pages/Home","format":"md","match":{"include":"high-quality-solutions"},"fields":[{"type":"string","name":"title","label":"Section Title","namespace":["highQualitySolutions","title"],"searchable":true,"uid":false},{"type":"object","name":"solutions","label":"Solutions","list":true,"fields":[{"type":"image","name":"image","label":"Image","namespace":["highQualitySolutions","solutions","image"],"searchable":false,"uid":false},{"type":"string","name":"title","label":"Solution Title","namespace":["highQualitySolutions","solutions","title"],"searchable":true,"uid":false},{"type":"string","name":"subtitle","label":"Solution Subtitle","namespace":["highQualitySolutions","solutions","subtitle"],"searchable":true,"uid":false}],"namespace":["highQualitySolutions","solutions"],"searchable":true,"uid":false}],"namespace":["highQualitySolutions"]},{"name":"whyWelcomecure","label":"Why Welcomecure","path":"content/pages/Home","format":"md","match":{"include":"why-welcomecure"},"fields":[{"type":"string","name":"title","label":"Main Title","namespace":["whyWelcomecure","title"],"searchable":true,"uid":false},{"type":"string","name":"subtitle","label":"Subtitle","namespace":["whyWelcomecure","subtitle"],"searchable":true,"uid":false},{"type":"image","name":"image","label":"Main Image","namespace":["whyWelcomecure","image"],"searchable":false,"uid":false},{"type":"string","name":"ctaText","label":"CTA Button Text","namespace":["whyWelcomecure","ctaText"],"searchable":true,"uid":false},{"type":"object","name":"features","label":"Features List","list":true,"fields":[{"type":"image","name":"icon","label":"Icon","namespace":["whyWelcomecure","features","icon"],"searchable":false,"uid":false},{"type":"string","name":"text","label":"Feature Text","namespace":["whyWelcomecure","features","text"],"searchable":true,"uid":false}],"namespace":["whyWelcomecure","features"],"searchable":true,"uid":false}],"namespace":["whyWelcomecure"]},{"name":"caseStudies","label":"Case Studies","path":"content/pages/Home","format":"md","match":{"include":"case-studies"},"fields":[{"type":"string","name":"title","label":"Main Title","namespace":["caseStudies","title"],"searchable":true,"uid":false},{"type":"string","name":"subtitle","label":"Subtitle","namespace":["caseStudies","subtitle"],"searchable":true,"uid":false},{"type":"object","name":"items","label":"Case Studies","list":true,"fields":[{"type":"image","name":"image","label":"Image","namespace":["caseStudies","items","image"],"searchable":false,"uid":false},{"type":"string","name":"title","label":"Title","namespace":["caseStudies","items","title"],"searchable":true,"uid":false},{"type":"string","name":"description","label":"Description","namespace":["caseStudies","items","description"],"searchable":true,"uid":false},{"type":"string","name":"publishDate","label":"Publish Date","namespace":["caseStudies","items","publishDate"],"searchable":true,"uid":false},{"type":"string","name":"publishBy","label":"Published By","namespace":["caseStudies","items","publishBy"],"searchable":true,"uid":false}],"namespace":["caseStudies","items"],"searchable":true,"uid":false}],"namespace":["caseStudies"]},{"name":"footer","label":"Footer","path":"content/components/Footer","format":"md","match":{"include":"footer"},"fields":[{"type":"string","name":"heading","label":"Newsletter Heading","namespace":["footer","heading"],"searchable":true,"uid":false},{"type":"string","name":"subheading","label":"Newsletter Subheading","namespace":["footer","subheading"],"searchable":true,"uid":false},{"type":"object","name":"socialLinks","label":"Social Links","list":true,"fields":[{"type":"image","name":"icon","label":"Social Icon","namespace":["footer","socialLinks","icon"],"searchable":false,"uid":false},{"type":"string","name":"url","label":"Social URL","namespace":["footer","socialLinks","url"],"searchable":true,"uid":false}],"namespace":["footer","socialLinks"],"searchable":true,"uid":false},{"type":"string","name":"emailPlaceholder","label":"Newsletter Email Placeholder","namespace":["footer","emailPlaceholder"],"searchable":true,"uid":false},{"type":"string","name":"newsletterButtonText","label":"Newsletter Button Text","namespace":["footer","newsletterButtonText"],"searchable":true,"uid":false},{"type":"object","name":"contactInfo","label":"Contact Info","fields":[{"type":"string","name":"email","label":"Email","namespace":["footer","contactInfo","email"],"searchable":true,"uid":false},{"type":"string","name":"phone","label":"Phone","namespace":["footer","contactInfo","phone"],"searchable":true,"uid":false}],"namespace":["footer","contactInfo"],"searchable":true,"uid":false},{"type":"object","name":"footerLinks","label":"Footer Link Sections","list":true,"fields":[{"type":"string","name":"title","label":"Section Title","namespace":["footer","footerLinks","title"],"searchable":true,"uid":false},{"type":"object","name":"links","label":"Links","list":true,"fields":[{"type":"string","name":"label","label":"Link Label","namespace":["footer","footerLinks","links","label"],"searchable":true,"uid":false},{"type":"string","name":"url","label":"Link URL","namespace":["footer","footerLinks","links","url"],"searchable":true,"uid":false}],"namespace":["footer","footerLinks","links"],"searchable":true,"uid":false}],"namespace":["footer","footerLinks"],"searchable":true,"uid":false},{"type":"object","name":"paymentMethods","label":"Payment Methods","list":true,"fields":[{"type":"image","name":"icon","label":"Payment Icon","namespace":["footer","paymentMethods","icon"],"searchable":false,"uid":false}],"namespace":["footer","paymentMethods"],"searchable":true,"uid":false},{"type":"string","name":"copyright","label":"Copyright Text","namespace":["footer","copyright"],"searchable":true,"uid":false},{"type":"object","name":"legalLinks","label":"Legal Links","list":true,"fields":[{"type":"string","name":"label","label":"Link Label","namespace":["footer","legalLinks","label"],"searchable":true,"uid":false},{"type":"string","name":"url","label":"Link URL","namespace":["footer","legalLinks","url"],"searchable":true,"uid":false}],"namespace":["footer","legalLinks"],"searchable":true,"uid":false}],"namespace":["footer"]},{"name":"seo","label":"SEO","path":"content/seo","format":"md","fields":[{"type":"string","name":"title","label":"Meta Title","namespace":["seo","title"],"searchable":true,"uid":false},{"type":"string","name":"description","label":"Meta Description","namespace":["seo","description"],"searchable":true,"uid":false},{"type":"object","name":"openGraph","label":"Open Graph","fields":[{"type":"string","name":"ogTitle","label":"OG Title","namespace":["seo","openGraph","ogTitle"],"searchable":true,"uid":false},{"type":"string","name":"ogDescription","label":"OG Description","namespace":["seo","openGraph","ogDescription"],"searchable":true,"uid":false},{"type":"image","name":"ogImage","label":"OG Image","namespace":["seo","openGraph","ogImage"],"searchable":false,"uid":false}],"namespace":["seo","openGraph"],"searchable":true,"uid":false},{"type":"object","name":"twitter","label":"Twitter Card","fields":[{"type":"string","name":"twitterTitle","label":"Twitter Title","namespace":["seo","twitter","twitterTitle"],"searchable":true,"uid":false},{"type":"string","name":"twitterDescription","label":"Twitter Description","namespace":["seo","twitter","twitterDescription"],"searchable":true,"uid":false},{"type":"image","name":"twitterImage","label":"Twitter Image","namespace":["seo","twitter","twitterImage"],"searchable":false,"uid":false}],"namespace":["seo","twitter"],"searchable":true,"uid":false}],"namespace":["seo"]}],"config":{"media":{"tina":{"publicFolder":"public","mediaRoot":""}}}}